[{"id":1,"url":"http://dummyimage.com/128x.png/5fa2dd/ffffff","title":"Upton Group"},
{"id":2,"url":"http://dummyimage.com/223x.png/ff4444/ffffff","title":"Hackett and Sons"},
{"id":3,"url":"http://dummyimage.com/207x.png/cc0000/ffffff","title":"Altenwerth-Mayer"},
{"id":4,"url":"http://dummyimage.com/235x.png/cc0000/ffffff","title":"Stiedemann-Thiel"},
{"id":5,"url":"http://dummyimage.com/169x.png/ff4444/ffffff","title":"Koss Inc"},
{"id":6,"url":"http://dummyimage.com/160x.png/ff4444/ffffff","title":"McLaughlin-VonRueden"},
{"id":7,"url":"http://dummyimage.com/206x.png/5fa2dd/ffffff","title":"Marks-Hamill"},
{"id":8,"url":"http://dummyimage.com/172x.png/dddddd/000000","title":"Kuvalis, Pouros and Kunze"},
{"id":9,"url":"http://dummyimage.com/131x.png/5fa2dd/ffffff","title":"Bartoletti LLC"},
{"id":10,"url":"http://dummyimage.com/193x.png/dddddd/000000","title":"Ledner-Terry"},
{"id":11,"url":"http://dummyimage.com/220x.png/cc0000/ffffff","title":"Weber, Breitenberg and Stroman"},
{"id":12,"url":"http://dummyimage.com/198x.png/cc0000/ffffff","title":"Schuppe-Haag"},
{"id":13,"url":"http://dummyimage.com/161x.png/ff4444/ffffff","title":"Boyer-Ledner"},
{"id":14,"url":"http://dummyimage.com/207x.png/cc0000/ffffff","title":"Konopelski-Thompson"},
{"id":15,"url":"http://dummyimage.com/221x.png/dddddd/000000","title":"Stiedemann, Brown and Howe"},
{"id":16,"url":"http://dummyimage.com/233x.png/5fa2dd/ffffff","title":"Fahey, Skiles and Walter"},
{"id":17,"url":"http://dummyimage.com/175x.png/5fa2dd/ffffff","title":"Schmidt-Gaylord"},
{"id":18,"url":"http://dummyimage.com/126x.png/dddddd/000000","title":"Toy-Hyatt"},
{"id":19,"url":"http://dummyimage.com/224x.png/cc0000/ffffff","title":"Grant and Sons"},
{"id":20,"url":"http://dummyimage.com/125x.png/5fa2dd/ffffff","title":"Collier, Willms and Hauck"},
{"id":21,"url":"http://dummyimage.com/136x.png/ff4444/ffffff","title":"Feest, Buckridge and Homenick"},
{"id":22,"url":"http://dummyimage.com/160x.png/5fa2dd/ffffff","title":"Mills-Bruen"},
{"id":23,"url":"http://dummyimage.com/155x.png/5fa2dd/ffffff","title":"Runolfsdottir and Sons"},
{"id":24,"url":"http://dummyimage.com/178x.png/5fa2dd/ffffff","title":"Konopelski LLC"},
{"id":25,"url":"http://dummyimage.com/130x.png/dddddd/000000","title":"Marks, Stroman and Heaney"},
{"id":26,"url":"http://dummyimage.com/228x.png/ff4444/ffffff","title":"Willms, Emmerich and Stanton"},
{"id":27,"url":"http://dummyimage.com/131x.png/5fa2dd/ffffff","title":"Krajcik-Torp"},
{"id":28,"url":"http://dummyimage.com/206x.png/dddddd/000000","title":"Huels-Moen"},
{"id":29,"url":"http://dummyimage.com/191x.png/5fa2dd/ffffff","title":"Jast, Quigley and Nader"},
{"id":30,"url":"http://dummyimage.com/234x.png/5fa2dd/ffffff","title":"Monahan, Pfannerstill and Christiansen"},
{"id":31,"url":"http://dummyimage.com/200x.png/dddddd/000000","title":"Johnson, Waelchi and Schuster"},
{"id":32,"url":"http://dummyimage.com/154x.png/5fa2dd/ffffff","title":"Pagac-Hahn"},
{"id":33,"url":"http://dummyimage.com/181x.png/ff4444/ffffff","title":"Wuckert-Davis"},
{"id":34,"url":"http://dummyimage.com/250x.png/cc0000/ffffff","title":"Feest-Gerlach"},
{"id":35,"url":"http://dummyimage.com/198x.png/dddddd/000000","title":"Yost and Sons"},
{"id":36,"url":"http://dummyimage.com/244x.png/cc0000/ffffff","title":"Ward-Friesen"},
{"id":37,"url":"http://dummyimage.com/199x.png/cc0000/ffffff","title":"Steuber, Conroy and Kemmer"},
{"id":38,"url":"http://dummyimage.com/165x.png/cc0000/ffffff","title":"Corkery-Daugherty"},
{"id":39,"url":"http://dummyimage.com/135x.png/ff4444/ffffff","title":"Hagenes-Keeling"},
{"id":40,"url":"http://dummyimage.com/129x.png/cc0000/ffffff","title":"Nikolaus, Towne and Rosenbaum"},
{"id":41,"url":"http://dummyimage.com/162x.png/ff4444/ffffff","title":"Flatley, Runolfsdottir and Walsh"},
{"id":42,"url":"http://dummyimage.com/197x.png/dddddd/000000","title":"Wyman Inc"},
{"id":43,"url":"http://dummyimage.com/205x.png/ff4444/ffffff","title":"Bernier Group"},
{"id":44,"url":"http://dummyimage.com/155x.png/dddddd/000000","title":"Stoltenberg, Gorczany and Harvey"},
{"id":45,"url":"http://dummyimage.com/234x.png/5fa2dd/ffffff","title":"Pollich Group"},
{"id":46,"url":"http://dummyimage.com/220x.png/5fa2dd/ffffff","title":"Dibbert-Sauer"},
{"id":47,"url":"http://dummyimage.com/191x.png/ff4444/ffffff","title":"Cummings, Grant and Hegmann"},
{"id":48,"url":"http://dummyimage.com/143x.png/cc0000/ffffff","title":"Pfannerstill LLC"},
{"id":49,"url":"http://dummyimage.com/171x.png/cc0000/ffffff","title":"O'Reilly-Davis"},
{"id":50,"url":"http://dummyimage.com/196x.png/cc0000/ffffff","title":"Terry, Christiansen and Spencer"},
{"id":51,"url":"http://dummyimage.com/126x.png/dddddd/000000","title":"Gerhold LLC"},
{"id":52,"url":"http://dummyimage.com/162x.png/dddddd/000000","title":"Beahan and Sons"},
{"id":53,"url":"http://dummyimage.com/143x.png/ff4444/ffffff","title":"Grimes-Ratke"},
{"id":54,"url":"http://dummyimage.com/229x.png/5fa2dd/ffffff","title":"Keebler-Jacobi"},
{"id":55,"url":"http://dummyimage.com/209x.png/dddddd/000000","title":"Johnston-Gerhold"},
{"id":56,"url":"http://dummyimage.com/167x.png/ff4444/ffffff","title":"Quigley Group"},
{"id":57,"url":"http://dummyimage.com/169x.png/dddddd/000000","title":"Lakin Group"},
{"id":58,"url":"http://dummyimage.com/216x.png/cc0000/ffffff","title":"Larkin, Yundt and Braun"},
{"id":59,"url":"http://dummyimage.com/248x.png/ff4444/ffffff","title":"Botsford, Wunsch and Padberg"},
{"id":60,"url":"http://dummyimage.com/191x.png/cc0000/ffffff","title":"Swift, Wiza and Schumm"},
{"id":61,"url":"http://dummyimage.com/219x.png/dddddd/000000","title":"Torp, Mills and Goldner"},
{"id":62,"url":"http://dummyimage.com/195x.png/ff4444/ffffff","title":"Fahey-Bins"},
{"id":63,"url":"http://dummyimage.com/160x.png/5fa2dd/ffffff","title":"Lynch Group"},
{"id":64,"url":"http://dummyimage.com/197x.png/5fa2dd/ffffff","title":"Hettinger-Bechtelar"},
{"id":65,"url":"http://dummyimage.com/145x.png/cc0000/ffffff","title":"Hammes, Crona and Christiansen"},
{"id":66,"url":"http://dummyimage.com/185x.png/cc0000/ffffff","title":"Schmeler LLC"},
{"id":67,"url":"http://dummyimage.com/245x.png/5fa2dd/ffffff","title":"Stracke-Thiel"},
{"id":68,"url":"http://dummyimage.com/130x.png/ff4444/ffffff","title":"Dietrich LLC"},
{"id":69,"url":"http://dummyimage.com/175x.png/5fa2dd/ffffff","title":"Collins-Dickens"},
{"id":70,"url":"http://dummyimage.com/192x.png/5fa2dd/ffffff","title":"Rath, Turner and Quitzon"},
{"id":71,"url":"http://dummyimage.com/220x.png/5fa2dd/ffffff","title":"McKenzie-Johnson"},
{"id":72,"url":"http://dummyimage.com/136x.png/ff4444/ffffff","title":"Okuneva-Abbott"},
{"id":73,"url":"http://dummyimage.com/212x.png/5fa2dd/ffffff","title":"Adams Inc"},
{"id":74,"url":"http://dummyimage.com/219x.png/5fa2dd/ffffff","title":"McKenzie Group"},
{"id":75,"url":"http://dummyimage.com/138x.png/ff4444/ffffff","title":"Hettinger-Rath"},
{"id":76,"url":"http://dummyimage.com/210x.png/ff4444/ffffff","title":"Orn-Purdy"},
{"id":77,"url":"http://dummyimage.com/201x.png/5fa2dd/ffffff","title":"Erdman, Heidenreich and Schuppe"},
{"id":78,"url":"http://dummyimage.com/147x.png/dddddd/000000","title":"Lindgren, Blick and Howe"},
{"id":79,"url":"http://dummyimage.com/203x.png/cc0000/ffffff","title":"Adams, Mueller and Oberbrunner"},
{"id":80,"url":"http://dummyimage.com/143x.png/5fa2dd/ffffff","title":"Lebsack LLC"},
{"id":81,"url":"http://dummyimage.com/234x.png/5fa2dd/ffffff","title":"Block, Skiles and Buckridge"},
{"id":82,"url":"http://dummyimage.com/249x.png/5fa2dd/ffffff","title":"Daugherty Group"},
{"id":83,"url":"http://dummyimage.com/142x.png/5fa2dd/ffffff","title":"Boehm, Senger and Prohaska"},
{"id":84,"url":"http://dummyimage.com/167x.png/cc0000/ffffff","title":"Satterfield-Corkery"},
{"id":85,"url":"http://dummyimage.com/206x.png/ff4444/ffffff","title":"Little Group"},
{"id":86,"url":"http://dummyimage.com/137x.png/dddddd/000000","title":"Hilpert LLC"},
{"id":87,"url":"http://dummyimage.com/208x.png/ff4444/ffffff","title":"Blick-Schultz"},
{"id":88,"url":"http://dummyimage.com/175x.png/5fa2dd/ffffff","title":"Maggio, Reynolds and Powlowski"},
{"id":89,"url":"http://dummyimage.com/125x.png/cc0000/ffffff","title":"Quitzon-Mosciski"},
{"id":90,"url":"http://dummyimage.com/156x.png/dddddd/000000","title":"Moen, Cassin and Ferry"},
{"id":91,"url":"http://dummyimage.com/219x.png/ff4444/ffffff","title":"Hintz LLC"},
{"id":92,"url":"http://dummyimage.com/202x.png/dddddd/000000","title":"D'Amore-Labadie"},
{"id":93,"url":"http://dummyimage.com/209x.png/5fa2dd/ffffff","title":"Rolfson and Sons"},
{"id":94,"url":"http://dummyimage.com/181x.png/cc0000/ffffff","title":"Effertz LLC"},
{"id":95,"url":"http://dummyimage.com/191x.png/ff4444/ffffff","title":"Schoen, Smith and Kerluke"},
{"id":96,"url":"http://dummyimage.com/185x.png/dddddd/000000","title":"Kessler-Luettgen"},
{"id":97,"url":"http://dummyimage.com/201x.png/cc0000/ffffff","title":"Yost-Kovacek"},
{"id":98,"url":"http://dummyimage.com/235x.png/cc0000/ffffff","title":"Block Inc"},
{"id":99,"url":"http://dummyimage.com/239x.png/cc0000/ffffff","title":"Stracke-Barton"},
{"id":100,"url":"http://dummyimage.com/227x.png/ff4444/ffffff","title":"Runolfsson Inc"},
{"id":101,"url":"http://dummyimage.com/221x.png/cc0000/ffffff","title":"Schmidt and Sons"},
{"id":102,"url":"http://dummyimage.com/187x.png/dddddd/000000","title":"Gaylord-Kovacek"},
{"id":103,"url":"http://dummyimage.com/155x.png/dddddd/000000","title":"Harris, Waelchi and O'Kon"},
{"id":104,"url":"http://dummyimage.com/182x.png/dddddd/000000","title":"Daniel LLC"},
{"id":105,"url":"http://dummyimage.com/139x.png/dddddd/000000","title":"Romaguera, Koelpin and Becker"},
{"id":106,"url":"http://dummyimage.com/197x.png/cc0000/ffffff","title":"Buckridge-Bradtke"},
{"id":107,"url":"http://dummyimage.com/157x.png/dddddd/000000","title":"Barrows Inc"},
{"id":108,"url":"http://dummyimage.com/217x.png/dddddd/000000","title":"Rowe-Mayer"},
{"id":109,"url":"http://dummyimage.com/179x.png/5fa2dd/ffffff","title":"Hintz Group"},
{"id":110,"url":"http://dummyimage.com/212x.png/cc0000/ffffff","title":"Kozey, Heller and Gusikowski"},
{"id":111,"url":"http://dummyimage.com/149x.png/dddddd/000000","title":"Feeney LLC"},
{"id":112,"url":"http://dummyimage.com/186x.png/dddddd/000000","title":"Balistreri, McCullough and Schmitt"},
{"id":113,"url":"http://dummyimage.com/148x.png/ff4444/ffffff","title":"Reichert Inc"},
{"id":114,"url":"http://dummyimage.com/159x.png/cc0000/ffffff","title":"Graham-Little"},
{"id":115,"url":"http://dummyimage.com/173x.png/5fa2dd/ffffff","title":"Bailey, Prohaska and Rutherford"},
{"id":116,"url":"http://dummyimage.com/237x.png/ff4444/ffffff","title":"Wyman Group"},
{"id":117,"url":"http://dummyimage.com/222x.png/cc0000/ffffff","title":"Raynor, Bergnaum and Rosenbaum"},
{"id":118,"url":"http://dummyimage.com/209x.png/5fa2dd/ffffff","title":"Watsica Inc"},
{"id":119,"url":"http://dummyimage.com/206x.png/5fa2dd/ffffff","title":"Little Inc"},
{"id":120,"url":"http://dummyimage.com/160x.png/ff4444/ffffff","title":"Fadel-Wolff"},
{"id":121,"url":"http://dummyimage.com/135x.png/5fa2dd/ffffff","title":"Lubowitz-Lynch"},
{"id":122,"url":"http://dummyimage.com/208x.png/ff4444/ffffff","title":"Rath Group"},
{"id":123,"url":"http://dummyimage.com/139x.png/dddddd/000000","title":"Pagac and Sons"},
{"id":124,"url":"http://dummyimage.com/216x.png/cc0000/ffffff","title":"Rath LLC"},
{"id":125,"url":"http://dummyimage.com/156x.png/cc0000/ffffff","title":"Doyle Inc"},
{"id":126,"url":"http://dummyimage.com/130x.png/5fa2dd/ffffff","title":"Baumbach LLC"},
{"id":127,"url":"http://dummyimage.com/238x.png/ff4444/ffffff","title":"Quigley, Schroeder and Konopelski"},
{"id":128,"url":"http://dummyimage.com/180x.png/cc0000/ffffff","title":"Watsica, Witting and Veum"},
{"id":129,"url":"http://dummyimage.com/223x.png/cc0000/ffffff","title":"Christiansen LLC"},
{"id":130,"url":"http://dummyimage.com/182x.png/5fa2dd/ffffff","title":"Carter-Reichel"},
{"id":131,"url":"http://dummyimage.com/139x.png/ff4444/ffffff","title":"Kassulke and Sons"},
{"id":132,"url":"http://dummyimage.com/248x.png/dddddd/000000","title":"Mante Inc"},
{"id":133,"url":"http://dummyimage.com/223x.png/5fa2dd/ffffff","title":"Johns-Daugherty"},
{"id":134,"url":"http://dummyimage.com/185x.png/ff4444/ffffff","title":"Maggio, Maggio and Dicki"},
{"id":135,"url":"http://dummyimage.com/224x.png/5fa2dd/ffffff","title":"Rath, Runolfsson and Skiles"},
{"id":136,"url":"http://dummyimage.com/162x.png/5fa2dd/ffffff","title":"Altenwerth-Keeling"},
{"id":137,"url":"http://dummyimage.com/219x.png/5fa2dd/ffffff","title":"Rutherford-Runolfsson"},
{"id":138,"url":"http://dummyimage.com/205x.png/cc0000/ffffff","title":"Beahan-McGlynn"},
{"id":139,"url":"http://dummyimage.com/139x.png/cc0000/ffffff","title":"Buckridge-Wiegand"},
{"id":140,"url":"http://dummyimage.com/137x.png/cc0000/ffffff","title":"Williamson, Mann and Monahan"},
{"id":141,"url":"http://dummyimage.com/249x.png/cc0000/ffffff","title":"Stoltenberg Inc"},
{"id":142,"url":"http://dummyimage.com/236x.png/5fa2dd/ffffff","title":"Reinger Group"},
{"id":143,"url":"http://dummyimage.com/126x.png/ff4444/ffffff","title":"Breitenberg, Hansen and Hyatt"},
{"id":144,"url":"http://dummyimage.com/166x.png/dddddd/000000","title":"Gleason LLC"},
{"id":145,"url":"http://dummyimage.com/206x.png/cc0000/ffffff","title":"Jaskolski, Kessler and Cassin"},
{"id":146,"url":"http://dummyimage.com/177x.png/dddddd/000000","title":"Dickinson-Kling"},
{"id":147,"url":"http://dummyimage.com/243x.png/dddddd/000000","title":"Boyer Inc"},
{"id":148,"url":"http://dummyimage.com/248x.png/ff4444/ffffff","title":"Price, Keeling and Lehner"},
{"id":149,"url":"http://dummyimage.com/180x.png/5fa2dd/ffffff","title":"Parisian Inc"},
{"id":150,"url":"http://dummyimage.com/245x.png/cc0000/ffffff","title":"Trantow, Wunsch and Lebsack"},
{"id":151,"url":"http://dummyimage.com/155x.png/ff4444/ffffff","title":"Cummerata-Bruen"},
{"id":152,"url":"http://dummyimage.com/159x.png/cc0000/ffffff","title":"Thompson, Goodwin and Bosco"},
{"id":153,"url":"http://dummyimage.com/156x.png/cc0000/ffffff","title":"Windler and Sons"},
{"id":154,"url":"http://dummyimage.com/185x.png/cc0000/ffffff","title":"Fritsch, Mosciski and Rath"},
{"id":155,"url":"http://dummyimage.com/243x.png/ff4444/ffffff","title":"Hettinger-Kreiger"},
{"id":156,"url":"http://dummyimage.com/233x.png/cc0000/ffffff","title":"Douglas, Stark and Denesik"},
{"id":157,"url":"http://dummyimage.com/167x.png/5fa2dd/ffffff","title":"Funk, Howell and Oberbrunner"},
{"id":158,"url":"http://dummyimage.com/184x.png/5fa2dd/ffffff","title":"Block Inc"},
{"id":159,"url":"http://dummyimage.com/245x.png/cc0000/ffffff","title":"Dickinson Group"},
{"id":160,"url":"http://dummyimage.com/197x.png/cc0000/ffffff","title":"Wunsch-Grady"},
{"id":161,"url":"http://dummyimage.com/133x.png/dddddd/000000","title":"Sawayn Group"},
{"id":162,"url":"http://dummyimage.com/201x.png/dddddd/000000","title":"Marquardt, Brown and O'Connell"},
{"id":163,"url":"http://dummyimage.com/148x.png/cc0000/ffffff","title":"Botsford LLC"},
{"id":164,"url":"http://dummyimage.com/172x.png/ff4444/ffffff","title":"Luettgen Inc"},
{"id":165,"url":"http://dummyimage.com/243x.png/5fa2dd/ffffff","title":"McGlynn LLC"},
{"id":166,"url":"http://dummyimage.com/205x.png/cc0000/ffffff","title":"Welch-Marks"},
{"id":167,"url":"http://dummyimage.com/205x.png/ff4444/ffffff","title":"Dach and Sons"},
{"id":168,"url":"http://dummyimage.com/172x.png/5fa2dd/ffffff","title":"Shields and Sons"},
{"id":169,"url":"http://dummyimage.com/170x.png/cc0000/ffffff","title":"Legros-Haley"},
{"id":170,"url":"http://dummyimage.com/180x.png/cc0000/ffffff","title":"Huel Group"},
{"id":171,"url":"http://dummyimage.com/183x.png/5fa2dd/ffffff","title":"Pollich-Flatley"},
{"id":172,"url":"http://dummyimage.com/200x.png/dddddd/000000","title":"Larson-Schumm"},
{"id":173,"url":"http://dummyimage.com/220x.png/dddddd/000000","title":"Boehm, Friesen and Hyatt"},
{"id":174,"url":"http://dummyimage.com/157x.png/5fa2dd/ffffff","title":"Bradtke-Schaefer"},
{"id":175,"url":"http://dummyimage.com/151x.png/cc0000/ffffff","title":"Grady-Heidenreich"},
{"id":176,"url":"http://dummyimage.com/167x.png/cc0000/ffffff","title":"Rodriguez, Champlin and Murazik"},
{"id":177,"url":"http://dummyimage.com/139x.png/5fa2dd/ffffff","title":"Ortiz, Haag and Hammes"},
{"id":178,"url":"http://dummyimage.com/189x.png/cc0000/ffffff","title":"Schiller-Grady"},
{"id":179,"url":"http://dummyimage.com/182x.png/5fa2dd/ffffff","title":"Davis, Pagac and Hauck"},
{"id":180,"url":"http://dummyimage.com/133x.png/5fa2dd/ffffff","title":"Rohan, Reilly and Gusikowski"},
{"id":181,"url":"http://dummyimage.com/153x.png/5fa2dd/ffffff","title":"Welch and Sons"},
{"id":182,"url":"http://dummyimage.com/167x.png/cc0000/ffffff","title":"Ward-Graham"},
{"id":183,"url":"http://dummyimage.com/243x.png/5fa2dd/ffffff","title":"O'Hara-Hudson"},
{"id":184,"url":"http://dummyimage.com/223x.png/dddddd/000000","title":"Shanahan-Olson"},
{"id":185,"url":"http://dummyimage.com/226x.png/cc0000/ffffff","title":"Stoltenberg and Sons"},
{"id":186,"url":"http://dummyimage.com/181x.png/cc0000/ffffff","title":"Koepp and Sons"},
{"id":187,"url":"http://dummyimage.com/184x.png/ff4444/ffffff","title":"Deckow-Kilback"},
{"id":188,"url":"http://dummyimage.com/207x.png/cc0000/ffffff","title":"Schmidt-Cole"},
{"id":189,"url":"http://dummyimage.com/162x.png/cc0000/ffffff","title":"Hilll Inc"},
{"id":190,"url":"http://dummyimage.com/210x.png/ff4444/ffffff","title":"Krajcik, Gutkowski and Wilkinson"},
{"id":191,"url":"http://dummyimage.com/149x.png/dddddd/000000","title":"Price LLC"},
{"id":192,"url":"http://dummyimage.com/211x.png/cc0000/ffffff","title":"Gulgowski, Schowalter and Anderson"},
{"id":193,"url":"http://dummyimage.com/164x.png/ff4444/ffffff","title":"O'Keefe-Moore"},
{"id":194,"url":"http://dummyimage.com/139x.png/ff4444/ffffff","title":"Bartell Group"},
{"id":195,"url":"http://dummyimage.com/191x.png/ff4444/ffffff","title":"Erdman-Kirlin"},
{"id":196,"url":"http://dummyimage.com/145x.png/cc0000/ffffff","title":"Weissnat, Thiel and Lebsack"},
{"id":197,"url":"http://dummyimage.com/213x.png/ff4444/ffffff","title":"Windler-Grant"},
{"id":198,"url":"http://dummyimage.com/132x.png/5fa2dd/ffffff","title":"Miller-Predovic"},
{"id":199,"url":"http://dummyimage.com/219x.png/cc0000/ffffff","title":"Purdy Inc"},
{"id":200,"url":"http://dummyimage.com/243x.png/cc0000/ffffff","title":"Jast-Conn"}]